[{"id":1228077200,"node_id":"R_kgDOSTL4kA","name":"ecommerce-sales","full_name":"vasi2904k/ecommerce-sales","private":false,"owner":{"login":"vasi2904k","id":191118882,"node_id":"U_kgDOC2Q-Ig","avatar_url":"https://avatars.githubusercontent.com/u/191118882?v=4","gravatar_id":"","url":"https://api.github.com/users/vasi2904k","html_url":"https://github.com/vasi2904k","followers_url":"https://api.github.com/users/vasi2904k/followers","following_url":"https://api.github.com/users/vasi2904k/following{/other_user}","gists_url":"https://api.github.com/users/vasi2904k/gists{/gist_id}","starred_url":"https://api.github.com/users/vasi2904k/starred{/owner}{/repo}","subscriptions_url":"https://api.github.com/users/vasi2904k/subscriptions","organizations_url":"https://api.github.com/users/vasi2904k/orgs","repos_url":"https://api.github.com/users/vasi2904k/repos","events_url":"https://api.github.com/users/vasi2904k/events{/privacy}","received_events_url":"https://api.github.com/users/vasi2904k/received_events","type":"User","user_view_type":"public","site_admin":false},"html_url":"https://github.com/vasi2904k/ecommerce-sales","description":"amazon, e-commerce, eda, data-preprocessing, feature-engineering, visualization, pandas, scikit-learn","fork":false,"url":"https://api.github.com/repos/vasi2904k/ecommerce-sales","forks_url":"https://api.github.com/repos/vasi2904k/ecommerce-sales/forks","keys_url":"https://api.github.com/repos/vasi2904k/ecommerce-sales/keys{/key_id}","collaborators_url":"https://api.github.com/repos/vasi2904k/ecommerce-sales/collaborators{/collaborator}","teams_url":"https://api.github.com/repos/vasi2904k/ecommerce-sales/teams","hooks_url":"https://api.github.com/repos/vasi2904k/ecommerce-sales/hooks","issue_events_url":"https://api.github.com/repos/vasi2904k/ecommerce-sales/issues/events{/number}","events_url":"https://api.github.com/repos/vasi2904k/ecommerce-sales/events","assignees_url":"https://api.github.com/repos/vasi2904k/ecommerce-sales/assignees{/user}","branches_url":"https://api.github.com/repos/vasi2904k/ecommerce-sales/branches{/branch}","tags_url":"https://api.github.com/repos/vasi2904k/ecommerce-sales/tags","blobs_url":"https://api.github.com/repos/vasi2904k/ecommerce-sales/git/blobs{/sha}","git_tags_url":"https://api.github.com/repos/vasi2904k/ecommerce-sales/git/tags{/sha}","git_refs_url":"https://api.github.com/repos/vasi2904k/ecommerce-sales/git/refs{/sha}","trees_url":"https://api.github.com/repos/vasi2904k/ecommerce-sales/git/trees{/sha}","statuses_url":"https://api.github.com/repos/vasi2904k/ecommerce-sales/statuses/{sha}","languages_url":"https://api.github.com/repos/vasi2904k/ecommerce-sales/languages","stargazers_url":"https://api.github.com/repos/vasi2904k/ecommerce-sales/stargazers","contributors_url":"https://api.github.com/repos/vasi2904k/ecommerce-sales/contributors","subscribers_url":"https://api.github.com/repos/vasi2904k/ecommerce-sales/subscribers","subscription_url":"https://api.github.com/repos/vasi2904k/ecommerce-sales/subscription","commits_url":"https://api.github.com/repos/vasi2904k/ecommerce-sales/commits{/sha}","git_commits_url":"https://api.github.com/repos/vasi2904k/ecommerce-sales/git/commits{/sha}","comments_url":"https://api.github.com/repos/vasi2904k/ecommerce-sales/comments{/number}","issue_comment_url":"https://api.github.com/repos/vasi2904k/ecommerce-sales/issues/comments{/number}","contents_url":"https://api.github.com/repos/vasi2904k/ecommerce-sales/contents/{+path}","compare_url":"https://api.github.com/repos/vasi2904k/ecommerce-sales/compare/{base}...{head}","merges_url":"https://api.github.com/repos/vasi2904k/ecommerce-sales/merges","archive_url":"https://api.github.com/repos/vasi2904k/ecommerce-sales/{archive_format}{/ref}","downloads_url":"https://api.github.com/repos/vasi2904k/ecommerce-sales/downloads","issues_url":"https://api.github.com/repos/vasi2904k/ecommerce-sales/issues{/number}","pulls_url":"https://api.github.com/repos/vasi2904k/ecommerce-sales/pulls{/number}","milestones_url":"https://api.github.com/repos/vasi2904k/ecommerce-sales/milestones{/number}","notifications_url":"https://api.github.com/repos/vasi2904k/ecommerce-sales/notifications{?since,all,participating}","labels_url":"https://api.github.com/repos/vasi2904k/ecommerce-sales/labels{/name}","releases_url":"https://api.github.com/repos/vasi2904k/ecommerce-sales/releases{/id}","deployments_url":"https://api.github.com/repos/vasi2904k/ecommerce-sales/deployments","created_at":"2026-05-03T15:07:28Z","updated_at":"2026-05-03T15:36:54Z","pushed_at":"2026-05-03T15:36:49Z","git_url":"git://github.com/vasi2904k/ecommerce-sales.git","ssh_url":"git@github.com:vasi2904k/ecommerce-sales.git","clone_url":"https://github.com/vasi2904k/ecommerce-sales.git","svn_url":"https://github.com/vasi2904k/ecommerce-sales","homepage":null,"size":0,"stargazers_count":0,"watchers_count":0,"language":"Jupyter Notebook","has_issues":true,"has_projects":true,"has_downloads":true,"has_wiki":true,"has_pages":false,"has_discussions":false,"forks_count":0,"mirror_url":null,"archived":false,"disabled":false,"open_issues_count":0,"license":null,"allow_forking":true,"is_template":false,"web_commit_signoff_required":false,"has_pull_requests":true,"pull_request_creation_policy":"all","topics":[],"visibility":"public","forks":0,"open_issues":0,"watchers":0,"default_branch":"main"},{"id":1213466620,"node_id":"R_kgDOSFQH_A","name":"AgroLens-AI","full_name":"vasi2904k/AgroLens-AI","private":false,"owner":{"login":"vasi2904k","id":191118882,"node_id":"U_kgDOC2Q-Ig","avatar_url":"https://avatars.githubusercontent.com/u/191118882?v=4","gravatar_id":"","url":"https://api.github.com/users/vasi2904k","html_url":"https://github.com/vasi2904k","followers_url":"https://api.github.com/users/vasi2904k/followers","following_url":"https://api.github.com/users/vasi2904k/following{/other_user}","gists_url":"https://api.github.com/users/vasi2904k/gists{/gist_id}","starred_url":"https://api.github.com/users/vasi2904k/starred{/owner}{/repo}","subscriptions_url":"https://api.github.com/users/vasi2904k/subscriptions","organizations_url":"https://api.github.com/users/vasi2904k/orgs","repos_url":"https://api.github.com/users/vasi2904k/repos","events_url":"https://api.github.com/users/vasi2904k/events{/privacy}","received_events_url":"https://api.github.com/users/vasi2904k/received_events","type":"User","user_view_type":"public","site_admin":false},"html_url":"https://github.com/vasi2904k/AgroLens-AI","description":"An end-to-end Computer Vision system utilizing Deep Learning to automate crop disease detection. This project implements custom CNN architectures and Transfer Learning to provide early-stage diagnostics, aimed at mitigating global yield loss and promoting sustainable agricultural practices.","fork":true,"url":"https://api.github.com/repos/vasi2904k/AgroLens-AI","forks_url":"https://api.github.com/repos/vasi2904k/AgroLens-AI/forks","keys_url":"https://api.github.com/repos/vasi2904k/AgroLens-AI/keys{/key_id}","collaborators_url":"https://api.github.com/repos/vasi2904k/AgroLens-AI/collaborators{/collaborator}","teams_url":"https://api.github.com/repos/vasi2904k/AgroLens-AI/teams","hooks_url":"https://api.github.com/repos/vasi2904k/AgroLens-AI/hooks","issue_events_url":"https://api.github.com/repos/vasi2904k/AgroLens-AI/issues/events{/number}","events_url":"https://api.github.com/repos/vasi2904k/AgroLens-AI/events","assignees_url":"https://api.github.com/repos/vasi2904k/AgroLens-AI/assignees{/user}","branches_url":"https://api.github.com/repos/vasi2904k/AgroLens-AI/branches{/branch}","tags_url":"https://api.github.com/repos/vasi2904k/AgroLens-AI/tags","blobs_url":"https://api.github.com/repos/vasi2904k/AgroLens-AI/git/blobs{/sha}","git_tags_url":"https://api.github.com/repos/vasi2904k/AgroLens-AI/git/tags{/sha}","git_refs_url":"https://api.github.com/repos/vasi2904k/AgroLens-AI/git/refs{/sha}","trees_url":"https://api.github.com/repos/vasi2904k/AgroLens-AI/git/trees{/sha}","statuses_url":"https://api.github.com/repos/vasi2904k/AgroLens-AI/statuses/{sha}","languages_url":"https://api.github.com/repos/vasi2904k/AgroLens-AI/languages","stargazers_url":"https://api.github.com/repos/vasi2904k/AgroLens-AI/stargazers","contributors_url":"https://api.github.com/repos/vasi2904k/AgroLens-AI/contributors","subscribers_url":"https://api.github.com/repos/vasi2904k/AgroLens-AI/subscribers","subscription_url":"https://api.github.com/repos/vasi2904k/AgroLens-AI/subscription","commits_url":"https://api.github.com/repos/vasi2904k/AgroLens-AI/commits{/sha}","git_commits_url":"https://api.github.com/repos/vasi2904k/AgroLens-AI/git/commits{/sha}","comments_url":"https://api.github.com/repos/vasi2904k/AgroLens-AI/comments{/number}","issue_comment_url":"https://api.github.com/repos/vasi2904k/AgroLens-AI/issues/comments{/number}","contents_url":"https://api.github.com/repos/vasi2904k/AgroLens-AI/contents/{+path}","compare_url":"https://api.github.com/repos/vasi2904k/AgroLens-AI/compare/{base}...{head}","merges_url":"https://api.github.com/repos/vasi2904k/AgroLens-AI/merges","archive_url":"https://api.github.com/repos/vasi2904k/AgroLens-AI/{archive_format}{/ref}","downloads_url":"https://api.github.com/repos/vasi2904k/AgroLens-AI/downloads","issues_url":"https://api.github.com/repos/vasi2904k/AgroLens-AI/issues{/number}","pulls_url":"https://api.github.com/repos/vasi2904k/AgroLens-AI/pulls{/number}","milestones_url":"https://api.github.com/repos/vasi2904k/AgroLens-AI/milestones{/number}","notifications_url":"https://api.github.com/repos/vasi2904k/AgroLens-AI/notifications{?since,all,participating}","labels_url":"https://api.github.com/repos/vasi2904k/AgroLens-AI/labels{/name}","releases_url":"https://api.github.com/repos/vasi2904k/AgroLens-AI/releases{/id}","deployments_url":"https://api.github.com/repos/vasi2904k/AgroLens-AI/deployments","created_at":"2026-04-17T12:11:59Z","updated_at":"2026-05-03T07:49:30Z","pushed_at":"2026-05-03T07:49:25Z","git_url":"git://github.com/vasi2904k/AgroLens-AI.git","ssh_url":"git@github.com:vasi2904k/AgroLens-AI.git","clone_url":"https://github.com/vasi2904k/AgroLens-AI.git","svn_url":"https://github.com/vasi2904k/AgroLens-AI","homepage":null,"size":8071,"stargazers_count":1,"watchers_count":1,"language":"Jupyter Notebook","has_issues":false,"has_projects":true,"has_downloads":true,"has_wiki":true,"has_pages":false,"has_discussions":false,"forks_count":0,"mirror_url":null,"archived":false,"disabled":false,"open_issues_count":0,"license":{"key":"mit","name":"MIT License","spdx_id":"MIT","url":"https://api.github.com/licenses/mit","node_id":"MDc6TGljZW5zZTEz"},"allow_forking":true,"is_template":false,"web_commit_signoff_required":false,"has_pull_requests":true,"pull_request_creation_policy":"all","topics":[],"visibility":"public","forks":0,"open_issues":0,"watchers":1,"default_branch":"main"},{"id":1221925491,"node_id":"R_kgDOSNUacw","name":"Portfolio-Website","full_name":"vasi2904k/Portfolio-Website","private":false,"owner":{"login":"vasi2904k","id":191118882,"node_id":"U_kgDOC2Q-Ig","avatar_url":"https://avatars.githubusercontent.com/u/191118882?v=4","gravatar_id":"","url":"https://api.github.com/users/vasi2904k","html_url":"https://github.com/vasi2904k","followers_url":"https://api.github.com/users/vasi2904k/followers","following_url":"https://api.github.com/users/vasi2904k/following{/other_user}","gists_url":"https://api.github.com/users/vasi2904k/gists{/gist_id}","starred_url":"https://api.github.com/users/vasi2904k/starred{/owner}{/repo}","subscriptions_url":"https://api.github.com/users/vasi2904k/subscriptions","organizations_url":"https://api.github.com/users/vasi2904k/orgs","repos_url":"https://api.github.com/users/vasi2904k/repos","events_url":"https://api.github.com/users/vasi2904k/events{/privacy}","received_events_url":"https://api.github.com/users/vasi2904k/received_events","type":"User","user_view_type":"public","site_admin":false},"html_url":"https://github.com/vasi2904k/Portfolio-Website","description":"Modern AI-powered portfolio built with Next.js, featuring a real-time chatbot, dynamic project showcase, and clean, responsive design.","fork":false,"url":"https://api.github.com/repos/vasi2904k/Portfolio-Website","forks_url":"https://api.github.com/repos/vasi2904k/Portfolio-Website/forks","keys_url":"https://api.github.com/repos/vasi2904k/Portfolio-Website/keys{/key_id}","collaborators_url":"https://api.github.com/repos/vasi2904k/Portfolio-Website/collaborators{/collaborator}","teams_url":"https://api.github.com/repos/vasi2904k/Portfolio-Website/teams","hooks_url":"https://api.github.com/repos/vasi2904k/Portfolio-Website/hooks","issue_events_url":"https://api.github.com/repos/vasi2904k/Portfolio-Website/issues/events{/number}","events_url":"https://api.github.com/repos/vasi2904k/Portfolio-Website/events","assignees_url":"https://api.github.com/repos/vasi2904k/Portfolio-Website/assignees{/user}","branches_url":"https://api.github.com/repos/vasi2904k/Portfolio-Website/branches{/branch}","tags_url":"https://api.github.com/repos/vasi2904k/Portfolio-Website/tags","blobs_url":"https://api.github.com/repos/vasi2904k/Portfolio-Website/git/blobs{/sha}","git_tags_url":"https://api.github.com/repos/vasi2904k/Portfolio-Website/git/tags{/sha}","git_refs_url":"https://api.github.com/repos/vasi2904k/Portfolio-Website/git/refs{/sha}","trees_url":"https://api.github.com/repos/vasi2904k/Portfolio-Website/git/trees{/sha}","statuses_url":"https://api.github.com/repos/vasi2904k/Portfolio-Website/statuses/{sha}","languages_url":"https://api.github.com/repos/vasi2904k/Portfolio-Website/languages","stargazers_url":"https://api.github.com/repos/vasi2904k/Portfolio-Website/stargazers","contributors_url":"https://api.github.com/repos/vasi2904k/Portfolio-Website/contributors","subscribers_url":"https://api.github.com/repos/vasi2904k/Portfolio-Website/subscribers","subscription_url":"https://api.github.com/repos/vasi2904k/Portfolio-Website/subscription","commits_url":"https://api.github.com/repos/vasi2904k/Portfolio-Website/commits{/sha}","git_commits_url":"https://api.github.com/repos/vasi2904k/Portfolio-Website/git/commits{/sha}","comments_url":"https://api.github.com/repos/vasi2904k/Portfolio-Website/comments{/number}","issue_comment_url":"https://api.github.com/repos/vasi2904k/Portfolio-Website/issues/comments{/number}","contents_url":"https://api.github.com/repos/vasi2904k/Portfolio-Website/contents/{+path}","compare_url":"https://api.github.com/repos/vasi2904k/Portfolio-Website/compare/{base}...{head}","merges_url":"https://api.github.com/repos/vasi2904k/Portfolio-Website/merges","archive_url":"https://api.github.com/repos/vasi2904k/Portfolio-Website/{archive_format}{/ref}","downloads_url":"https://api.github.com/repos/vasi2904k/Portfolio-Website/downloads","issues_url":"https://api.github.com/repos/vasi2904k/Portfolio-Website/issues{/number}","pulls_url":"https://api.github.com/repos/vasi2904k/Portfolio-Website/pulls{/number}","milestones_url":"https://api.github.com/repos/vasi2904k/Portfolio-Website/milestones{/number}","notifications_url":"https://api.github.com/repos/vasi2904k/Portfolio-Website/notifications{?since,all,participating}","labels_url":"https://api.github.com/repos/vasi2904k/Portfolio-Website/labels{/name}","releases_url":"https://api.github.com/repos/vasi2904k/Portfolio-Website/releases{/id}","deployments_url":"https://api.github.com/repos/vasi2904k/Portfolio-Website/deployments","created_at":"2026-04-26T21:16:28Z","updated_at":"2026-04-30T21:18:34Z","pushed_at":"2026-04-30T21:18:29Z","git_url":"git://github.com/vasi2904k/Portfolio-Website.git","ssh_url":"git@github.com:vasi2904k/Portfolio-Website.git","clone_url":"https://github.com/vasi2904k/Portfolio-Website.git","svn_url":"https://github.com/vasi2904k/Portfolio-Website","homepage":"https://portfolio-website-gamma-ten-13.vercel.app","size":8245,"stargazers_count":1,"watchers_count":1,"language":"JavaScript","has_issues":true,"has_projects":true,"has_downloads":true,"has_wiki":true,"has_pages":false,"has_discussions":false,"forks_count":0,"mirror_url":null,"archived":false,"disabled":false,"open_issues_count":0,"license":null,"allow_forking":true,"is_template":false,"web_commit_signoff_required":false,"has_pull_requests":true,"pull_request_creation_policy":"all","topics":[],"visibility":"public","forks":0,"open_issues":0,"watchers":1,"default_branch":"main"},{"id":1225951180,"node_id":"R_kgDOSRKHzA","name":"Global-Pollution-Analysis","full_name":"vasi2904k/Global-Pollution-Analysis","private":false,"owner":{"login":"vasi2904k","id":191118882,"node_id":"U_kgDOC2Q-Ig","avatar_url":"https://avatars.githubusercontent.com/u/191118882?v=4","gravatar_id":"","url":"https://api.github.com/users/vasi2904k","html_url":"https://github.com/vasi2904k","followers_url":"https://api.github.com/users/vasi2904k/followers","following_url":"https://api.github.com/users/vasi2904k/following{/other_user}","gists_url":"https://api.github.com/users/vasi2904k/gists{/gist_id}","starred_url":"https://api.github.com/users/vasi2904k/starred{/owner}{/repo}","subscriptions_url":"https://api.github.com/users/vasi2904k/subscriptions","organizations_url":"https://api.github.com/users/vasi2904k/orgs","repos_url":"https://api.github.com/users/vasi2904k/repos","events_url":"https://api.github.com/users/vasi2904k/events{/privacy}","received_events_url":"https://api.github.com/users/vasi2904k/received_events","type":"User","user_view_type":"public","site_admin":false},"html_url":"https://github.com/vasi2904k/Global-Pollution-Analysis","description":"Machine learning analysis of global pollution data with EDA, feature engineering, and classification models","fork":false,"url":"https://api.github.com/repos/vasi2904k/Global-Pollution-Analysis","forks_url":"https://api.github.com/repos/vasi2904k/Global-Pollution-Analysis/forks","keys_url":"https://api.github.com/repos/vasi2904k/Global-Pollution-Analysis/keys{/key_id}","collaborators_url":"https://api.github.com/repos/vasi2904k/Global-Pollution-Analysis/collaborators{/collaborator}","teams_url":"https://api.github.com/repos/vasi2904k/Global-Pollution-Analysis/teams","hooks_url":"https://api.github.com/repos/vasi2904k/Global-Pollution-Analysis/hooks","issue_events_url":"https://api.github.com/repos/vasi2904k/Global-Pollution-Analysis/issues/events{/number}","events_url":"https://api.github.com/repos/vasi2904k/Global-Pollution-Analysis/events","assignees_url":"https://api.github.com/repos/vasi2904k/Global-Pollution-Analysis/assignees{/user}","branches_url":"https://api.github.com/repos/vasi2904k/Global-Pollution-Analysis/branches{/branch}","tags_url":"https://api.github.com/repos/vasi2904k/Global-Pollution-Analysis/tags","blobs_url":"https://api.github.com/repos/vasi2904k/Global-Pollution-Analysis/git/blobs{/sha}","git_tags_url":"https://api.github.com/repos/vasi2904k/Global-Pollution-Analysis/git/tags{/sha}","git_refs_url":"https://api.github.com/repos/vasi2904k/Global-Pollution-Analysis/git/refs{/sha}","trees_url":"https://api.github.com/repos/vasi2904k/Global-Pollution-Analysis/git/trees{/sha}","statuses_url":"https://api.github.com/repos/vasi2904k/Global-Pollution-Analysis/statuses/{sha}","languages_url":"https://api.github.com/repos/vasi2904k/Global-Pollution-Analysis/languages","stargazers_url":"https://api.github.com/repos/vasi2904k/Global-Pollution-Analysis/stargazers","contributors_url":"https://api.github.com/repos/vasi2904k/Global-Pollution-Analysis/contributors","subscribers_url":"https://api.github.com/repos/vasi2904k/Global-Pollution-Analysis/subscribers","subscription_url":"https://api.github.com/repos/vasi2904k/Global-Pollution-Analysis/subscription","commits_url":"https://api.github.com/repos/vasi2904k/Global-Pollution-Analysis/commits{/sha}","git_commits_url":"https://api.github.com/repos/vasi2904k/Global-Pollution-Analysis/git/commits{/sha}","comments_url":"https://api.github.com/repos/vasi2904k/Global-Pollution-Analysis/comments{/number}","issue_comment_url":"https://api.github.com/repos/vasi2904k/Global-Pollution-Analysis/issues/comments{/number}","contents_url":"https://api.github.com/repos/vasi2904k/Global-Pollution-Analysis/contents/{+path}","compare_url":"https://api.github.com/repos/vasi2904k/Global-Pollution-Analysis/compare/{base}...{head}","merges_url":"https://api.github.com/repos/vasi2904k/Global-Pollution-Analysis/merges","archive_url":"https://api.github.com/repos/vasi2904k/Global-Pollution-Analysis/{archive_format}{/ref}","downloads_url":"https://api.github.com/repos/vasi2904k/Global-Pollution-Analysis/downloads","issues_url":"https://api.github.com/repos/vasi2904k/Global-Pollution-Analysis/issues{/number}","pulls_url":"https://api.github.com/repos/vasi2904k/Global-Pollution-Analysis/pulls{/number}","milestones_url":"https://api.github.com/repos/vasi2904k/Global-Pollution-Analysis/milestones{/number}","notifications_url":"https://api.github.com/repos/vasi2904k/Global-Pollution-Analysis/notifications{?since,all,participating}","labels_url":"https://api.github.com/repos/vasi2904k/Global-Pollution-Analysis/labels{/name}","releases_url":"https://api.github.com/repos/vasi2904k/Global-Pollution-Analysis/releases{/id}","deployments_url":"https://api.github.com/repos/vasi2904k/Global-Pollution-Analysis/deployments","created_at":"2026-04-30T20:21:46Z","updated_at":"2026-04-30T20:27:54Z","pushed_at":"2026-04-30T20:22:45Z","git_url":"git://github.com/vasi2904k/Global-Pollution-Analysis.git","ssh_url":"git@github.com:vasi2904k/Global-Pollution-Analysis.git","clone_url":"https://github.com/vasi2904k/Global-Pollution-Analysis.git","svn_url":"https://github.com/vasi2904k/Global-Pollution-Analysis","homepage":"http://vasi-khan.vercel.app/","size":40024,"stargazers_count":0,"watchers_count":0,"language":"Jupyter Notebook","has_issues":true,"has_projects":true,"has_downloads":true,"has_wiki":true,"has_pages":false,"has_discussions":false,"forks_count":0,"mirror_url":null,"archived":false,"disabled":false,"open_issues_count":0,"license":null,"allow_forking":true,"is_template":false,"web_commit_signoff_required":false,"has_pull_requests":true,"pull_request_creation_policy":"all","topics":["classification","data-analysis","data-science","eda","logistic-regression","machine-learning","pandas","python","scikit-learn","seaborn"],"visibility":"public","forks":0,"open_issues":0,"watchers":0,"default_branch":"main"},{"id":1214237059,"node_id":"R_kgDOSF_Jgw","name":"Food-Delivery-Time-Prediction","full_name":"vasi2904k/Food-Delivery-Time-Prediction","private":false,"owner":{"login":"vasi2904k","id":191118882,"node_id":"U_kgDOC2Q-Ig","avatar_url":"https://avatars.githubusercontent.com/u/191118882?v=4","gravatar_id":"","url":"https://api.github.com/users/vasi2904k","html_url":"https://github.com/vasi2904k","followers_url":"https://api.github.com/users/vasi2904k/followers","following_url":"https://api.github.com/users/vasi2904k/following{/other_user}","gists_url":"https://api.github.com/users/vasi2904k/gists{/gist_id}","starred_url":"https://api.github.com/users/vasi2904k/starred{/owner}{/repo}","subscriptions_url":"https://api.github.com/users/vasi2904k/subscriptions","organizations_url":"https://api.github.com/users/vasi2904k/orgs","repos_url":"https://api.github.com/users/vasi2904k/repos","events_url":"https://api.github.com/users/vasi2904k/events{/privacy}","received_events_url":"https://api.github.com/users/vasi2904k/received_events","type":"User","user_view_type":"public","site_admin":false},"html_url":"https://github.com/vasi2904k/Food-Delivery-Time-Prediction","description":"ML project for predicting food delivery time using EDA, feature engineering, and models like Random Forest with performance comparison.","fork":false,"url":"https://api.github.com/repos/vasi2904k/Food-Delivery-Time-Prediction","forks_url":"https://api.github.com/repos/vasi2904k/Food-Delivery-Time-Prediction/forks","keys_url":"https://api.github.com/repos/vasi2904k/Food-Delivery-Time-Prediction/keys{/key_id}","collaborators_url":"https://api.github.com/repos/vasi2904k/Food-Delivery-Time-Prediction/collaborators{/collaborator}","teams_url":"https://api.github.com/repos/vasi2904k/Food-Delivery-Time-Prediction/teams","hooks_url":"https://api.github.com/repos/vasi2904k/Food-Delivery-Time-Prediction/hooks","issue_events_url":"https://api.github.com/repos/vasi2904k/Food-Delivery-Time-Prediction/issues/events{/number}","events_url":"https://api.github.com/repos/vasi2904k/Food-Delivery-Time-Prediction/events","assignees_url":"https://api.github.com/repos/vasi2904k/Food-Delivery-Time-Prediction/assignees{/user}","branches_url":"https://api.github.com/repos/vasi2904k/Food-Delivery-Time-Prediction/branches{/branch}","tags_url":"https://api.github.com/repos/vasi2904k/Food-Delivery-Time-Prediction/tags","blobs_url":"https://api.github.com/repos/vasi2904k/Food-Delivery-Time-Prediction/git/blobs{/sha}","git_tags_url":"https://api.github.com/repos/vasi2904k/Food-Delivery-Time-Prediction/git/tags{/sha}","git_refs_url":"https://api.github.com/repos/vasi2904k/Food-Delivery-Time-Prediction/git/refs{/sha}","trees_url":"https://api.github.com/repos/vasi2904k/Food-Delivery-Time-Prediction/git/trees{/sha}","statuses_url":"https://api.github.com/repos/vasi2904k/Food-Delivery-Time-Prediction/statuses/{sha}","languages_url":"https://api.github.com/repos/vasi2904k/Food-Delivery-Time-Prediction/languages","stargazers_url":"https://api.github.com/repos/vasi2904k/Food-Delivery-Time-Prediction/stargazers","contributors_url":"https://api.github.com/repos/vasi2904k/Food-Delivery-Time-Prediction/contributors","subscribers_url":"https://api.github.com/repos/vasi2904k/Food-Delivery-Time-Prediction/subscribers","subscription_url":"https://api.github.com/repos/vasi2904k/Food-Delivery-Time-Prediction/subscription","commits_url":"https://api.github.com/repos/vasi2904k/Food-Delivery-Time-Prediction/commits{/sha}","git_commits_url":"https://api.github.com/repos/vasi2904k/Food-Delivery-Time-Prediction/git/commits{/sha}","comments_url":"https://api.github.com/repos/vasi2904k/Food-Delivery-Time-Prediction/comments{/number}","issue_comment_url":"https://api.github.com/repos/vasi2904k/Food-Delivery-Time-Prediction/issues/comments{/number}","contents_url":"https://api.github.com/repos/vasi2904k/Food-Delivery-Time-Prediction/contents/{+path}","compare_url":"https://api.github.com/repos/vasi2904k/Food-Delivery-Time-Prediction/compare/{base}...{head}","merges_url":"https://api.github.com/repos/vasi2904k/Food-Delivery-Time-Prediction/merges","archive_url":"https://api.github.com/repos/vasi2904k/Food-Delivery-Time-Prediction/{archive_format}{/ref}","downloads_url":"https://api.github.com/repos/vasi2904k/Food-Delivery-Time-Prediction/downloads","issues_url":"https://api.github.com/repos/vasi2904k/Food-Delivery-Time-Prediction/issues{/number}","pulls_url":"https://api.github.com/repos/vasi2904k/Food-Delivery-Time-Prediction/pulls{/number}","milestones_url":"https://api.github.com/repos/vasi2904k/Food-Delivery-Time-Prediction/milestones{/number}","notifications_url":"https://api.github.com/repos/vasi2904k/Food-Delivery-Time-Prediction/notifications{?since,all,participating}","labels_url":"https://api.github.com/repos/vasi2904k/Food-Delivery-Time-Prediction/labels{/name}","releases_url":"https://api.github.com/repos/vasi2904k/Food-Delivery-Time-Prediction/releases{/id}","deployments_url":"https://api.github.com/repos/vasi2904k/Food-Delivery-Time-Prediction/deployments","created_at":"2026-04-18T09:48:51Z","updated_at":"2026-04-30T20:20:04Z","pushed_at":"2026-04-25T14:58:20Z","git_url":"git://github.com/vasi2904k/Food-Delivery-Time-Prediction.git","ssh_url":"git@github.com:vasi2904k/Food-Delivery-Time-Prediction.git","clone_url":"https://github.com/vasi2904k/Food-Delivery-Time-Prediction.git","svn_url":"https://github.com/vasi2904k/Food-Delivery-Time-Prediction","homepage":"","size":11448,"stargazers_count":1,"watchers_count":1,"language":"Jupyter Notebook","has_issues":true,"has_projects":true,"has_downloads":true,"has_wiki":true,"has_pages":false,"has_discussions":false,"forks_count":0,"mirror_url":null,"archived":false,"disabled":false,"open_issues_count":1,"license":null,"allow_forking":true,"is_template":false,"web_commit_signoff_required":false,"has_pull_requests":true,"pull_request_creation_policy":"all","topics":["classification","data-science","data-visualization","eda","feature-engineering","jupyter-notebook","linear-regression","logistic-regression","machine-learning","pandas","python","random-forest","regression","scikit-learn"],"visibility":"public","forks":0,"open_issues":1,"watchers":1,"default_branch":"main"}]

